README
setup.py
name_cleaver/__init__.py
name_cleaver/cleaver.py
name_cleaver/exception.py
name_cleaver/names.py
name_cleaver/nicknames.py
name_cleaver/test_name_cleaver.py
name_cleaver.egg-info/PKG-INFO
name_cleaver.egg-info/SOURCES.txt
name_cleaver.egg-info/dependency_links.txt
name_cleaver.egg-info/top_level.txt