Metadata-Version: 1.1
Name: name-cleaver
Version: 0.6.0
Summary: Name parser and formatter (for politicians, individuals, and organizations)
Home-page: http://github.com/sunlightlabs/name-cleaver/
Author: Alison Rowland
Author-email: arowland@sunlightfoundation.com
License: BSD License
Platform: any
Classifier: Development Status :: 4 - Beta
Classifier: Intended Audience :: Developers
Classifier: License :: OSI Approved :: BSD License
Classifier: Natural Language :: English
Classifier: Operating System :: OS Independent
Classifier: Programming Language :: Python
Classifier: Environment :: Web Environment
Classifier: Topic :: Text Processing :: Linguistic
